spotifyapi/__init__.py
spotifyapi/album.py
spotifyapi/artist.py
spotifyapi/audio_feature.py
spotifyapi/track.py
spotifyapi/utils.py
spotifyapi-0.0.1.dist-info/LICENSE
spotifyapi-0.0.1.dist-info/METADATA
spotifyapi-0.0.1.dist-info/WHEEL
spotifyapi-0.0.1.dist-info/top_level.txt
spotifyapi-0.0.1.dist-info/RECORD
