Metadata-Version: 2.1
Name: spotifyapi
Version: 0.0.1
Summary: A Python wrapper to interact the Spotify web API
Home-page: https://github.com/zackelia/spotifyapi
Author: Zack Elia
Author-email: pypi@zacharyelia.com
License: UNKNOWN
Platform: UNKNOWN
Classifier: Programming Language :: Python :: 3
Classifier: License :: OSI Approved :: GNU General Public License v3 (GPLv3)
Classifier: Operating System :: OS Independent
Requires-Dist: requests
